testmj/__init__.py
testmj/api_helper.py
testmj/configuration.py
testmj/decorators.py
testmj/testmj_client.py
testmj/controllers/__init__.py
testmj/controllers/base_controller.py
testmj/controllers/simple_calculator_controller.py
testmj/exceptions/__init__.py
testmj/exceptions/api_exception.py
testmj/http/__init__.py
testmj/http/http_call_back.py
testmj/http/http_client.py
testmj/http/http_context.py
testmj/http/http_method_enum.py
testmj/http/http_request.py
testmj/http/http_response.py
testmj/http/requests_client.py
testmj/models/__init__.py
testmj/models/operation_type_enum.py
tests/__init__.py
tests/http_response_catcher.py
tests/test_helper.py
tests/controllers/__init__.py
tests/controllers/controller_test_base.py
tests/controllers/test_simple_calculator_controller.py
testmj-1.dist-info/LICENSE
testmj-1.dist-info/METADATA
testmj-1.dist-info/WHEEL
testmj-1.dist-info/top_level.txt
testmj-1.dist-info/RECORD
